pakiet_szkoleniowy/__init__.py
pakiet_szkoleniowy/moj_modul1.py
pakiet_szkoleniowy/moj_modul2.py
pakiet_szkoleniowy-0.4.2.dist-info/LICENSE
pakiet_szkoleniowy-0.4.2.dist-info/METADATA
pakiet_szkoleniowy-0.4.2.dist-info/WHEEL
pakiet_szkoleniowy-0.4.2.dist-info/top_level.txt
pakiet_szkoleniowy-0.4.2.dist-info/RECORD
