Metadata-Version: 2.1
Name: pakiet-szkoleniowy
Version: 0.4.2
Summary: Kilka przydatnych funkcji zwracających czas w różnych postaciach
Home-page: https://github.com/angelm1974/Python-zajecia
Author: Mariusz Mol
Author-email: mariusz980@gmail.com
License: UNKNOWN
Platform: UNKNOWN
Classifier: Programming Language :: Python :: 3
Classifier: License :: OSI Approved :: MIT License
Classifier: Operating System :: OS Independent
Requires-Python: >=3.6
